berset_engine/__init__.py
berset_engine/better/__init__.py
berset_engine/better/assessment.py
berset_engine/better/benchmark.py
berset_engine/better/building.py
berset_engine/better/constants.py
berset_engine/better/model.py
berset_engine/better/portfolio.py
berset_engine/better/report.py
berset_engine/better/utility.py
berset_engine/better/weather.py
berset_engine/better/data/__init__.py
berset_engine/better/data/isd-history.txt
berset_engine/better/data/noaa_weather_station_list.csv
berset_engine/better/data/sample_benchmark_stats.json
berset_engine/better/templates/building_analytic_report_content.html
berset_engine/eequest/__init__.py
berset_engine/eequest/building_envelop.py
berset_engine/eequest/constants.py
berset_engine-2024.1004.dist-info/METADATA
berset_engine-2024.1004.dist-info/WHEEL
berset_engine-2024.1004.dist-info/top_level.txt
berset_engine-2024.1004.dist-info/RECORD
