Metadata-Version: 2.1
Name: berset_engine
Version: 2024.1004
Summary: Bulding Energy Retrofit Scenario Evaluation Tool Engine
Home-page: https://github.com/longlevan/berset_engine
Author: Van Long Le
Author-email: long.le-van@outlook.com
License: MIT
Project-URL: Documentation, https://github.com/longlevan/berset_engine/
Project-URL: Changelog, https://github.com/longlevan/berset_engine/CHANGELOG.md
Project-URL: Issue Tracker, https://github.com/longlevan/berset_engine/issues
Classifier: License :: OSI Approved :: MIT License
Classifier: Programming Language :: Python
Classifier: Programming Language :: Python :: 3.6
Classifier: Programming Language :: Python :: 3.7
Classifier: Programming Language :: Python :: Implementation :: CPython
Requires-Python: >=3.6.0
Requires-Dist: pandas >=2.0.0
Requires-Dist: geocoder >=1.38.1
Requires-Dist: ish-parser >=0.0.22
Requires-Dist: numpy >=1.20.0
Requires-Dist: scipy >=1.11.0
Requires-Dist: xlrd >=2.0.1
Requires-Dist: geopy >=2.4.1
Requires-Dist: python-dotenv >=1.0.1
Requires-Dist: plotly >=5.8.0
Requires-Dist: Jinja2 >=3.1.2
